{
  "totalBytes": { "name": "总流量", "unit": "BYTE", "kpi": "totalBytes" },
  "clientBytes": { "name": "客户端流量", "unit": "BYTE", "kpi": "clientBytes" },
  "serverBytes": { "name": "服务器流量", "unit": "BYTE", "kpi": "serverBytes" },
  "totalRate": { "name": "会话总速率", "unit": "BPS", "kpi": "totalRate" },
  "clientRate": {
    "name": "客户端会话速率",
    "unit": "BPS",
    "kpi": "clientRate"
  },
  "serverRate": {
    "name": "服务器会话速率",
    "unit": "BPS",
    "kpi": "serverRate"
  },
  "totalAvgRate": { "name": "平均速率", "unit": "BPS", "kpi": "totalAvgRate" },
  "clientAvgRate": {
    "name": "客户端平均速率",
    "unit": "BPS",
    "kpi": "clientAvgRate"
  },
  "serverAvgRate": {
    "name": "服务器平均速率",
    "unit": "BPS",
    "kpi": "serverAvgRate"
  },
  "totalPkts": { "name": "总数据包", "unit": "NUMBER", "kpi": "totalPkts" },
  "clientPkts": { "name": "客户端包数", "unit": "NUMBER", "kpi": "clientPkts" },
  "serverPkts": { "name": "服务器包数", "unit": "NUMBER", "kpi": "serverPkts" },
  "totalPktRate": { "name": "总包率", "unit": "PPS", "kpi": "totalPktRate" },
  "totalSegLostNum": {
    "name": "丢包总数",
    "unit": "NUMBER",
    "kpi": "totalSegLostNum"
  },
  "clientSegLostNum": {
    "name": "客户端丢包数量",
    "unit": "NUMBER",
    "kpi": "clientSegLostNum"
  },
  "serverSegLostNum": {
    "name": "服务器丢包数量",
    "unit": "NUMBER",
    "kpi": "serverSegLostNum"
  },
  "totalPayloadByteNum": {
    "name": "有效载荷",
    "unit": "BYTE",
    "kpi": "totalPayloadByteNum"
  },
  "clientPayloadByteNum": {
    "name": "客户端有效载荷",
    "unit": "BYTE",
    "kpi": "clientPayloadByteNum"
  },
  "serverPayloadByteNum": {
    "name": "服务器有效载荷",
    "unit": "BYTE",
    "kpi": "serverPayloadByteNum"
  },
  "totalDataPktNum": {
    "name": "负载数据包",
    "unit": "NUMBER",
    "kpi": "totalDataPktNum"
  },
  "clientDataPktNum": {
    "name": "客户端负载数据包",
    "unit": "NUMBER",
    "kpi": "clientDataPktNum"
  },
  "serverDataPktNum": {
    "name": "服务器负载数据包",
    "unit": "NUMBER",
    "kpi": "serverDataPktNum"
  },
  "bytesRespPercent": {
    "name": "字节收发比",
    "unit": "PERCENT",
    "kpi": "bytesRespPercent"
  },
  "pktsRespPercent": {
    "name": "数据包收发比",
    "unit": "PERCENT",
    "kpi": "pktsRespPercent"
  },
  "clientReqNum": { "name": "请求量", "unit": "NUMBER", "kpi": "clientReqNum" },
  "avgPktLen": { "name": "平均包长", "unit": "BYTE", "kpi": "avgPktLen" },
  "utilization": { "name": "利用率", "unit": "PERCENT", "kpi": "utilization" },
  "peakBps": { "name": "峰值速率", "unit": "STRING", "kpi": "peakBps" },
  "totalZeroWindow": {
    "name": "零窗口",
    "unit": "NUMBER",
    "kpi": "totalZeroWindow"
  },
  "clientZeroWindow": {
    "name": "客户端零窗口",
    "unit": "NUMBER",
    "kpi": "clientZeroWindow"
  },
  "serverZeroWindow": {
    "name": "服务器零窗口",
    "unit": "NUMBER",
    "kpi": "serverZeroWindow"
  },
  "totalRetx": { "name": "重传数量", "unit": "NUMBER", "kpi": "totalRetx" },
  "clientRetx": {
    "name": "客户端重传数量",
    "unit": "NUMBER",
    "kpi": "clientRetx"
  },
  "serverRetx": {
    "name": "服务器重传数量",
    "unit": "NUMBER",
    "kpi": "serverRetx"
  },
  "totalRetxRate": {
    "name": "重传率",
    "unit": "PERCENT",
    "kpi": "totalRetxRate"
  },
  "clientRetxRate": {
    "name": "客户端重传率",
    "unit": "PERCENT",
    "kpi": "clientRetxRate"
  },
  "serverRetxRate": {
    "name": "服务器重传率",
    "unit": "PERCENT",
    "kpi": "serverRetxRate"
  },
  "totalRst": { "name": "RST数量", "unit": "NUMBER", "kpi": "totalRst" },
  "clientRst": { "name": "客户端RST", "unit": "NUMBER", "kpi": "clientRst" },
  "serverRst": { "name": "服务器RST", "unit": "NUMBER", "kpi": "serverRst" },
  "clientSyn": { "name": "客户端SYN", "unit": "NUMBER", "kpi": "clientSyn" },
  "serverSyn": { "name": "服务器SYN", "unit": "NUMBER", "kpi": "serverSyn" },
  "totalFin": { "name": "TCP FIN", "unit": "NUMBER", "kpi": "totalFin" },
  "clientFin": {
    "name": "FIN客户端数量",
    "unit": "NUMBER",
    "kpi": "clientFin"
  },
  "serverFin": {
    "name": "FIN服务器数量",
    "unit": "NUMBER",
    "kpi": "serverFin"
  },
  "failServerRstNum": {
    "name": "建连失败数-服务器RST",
    "unit": "NUMBER",
    "kpi": "failServerRstNum"
  },
  "failClientRstNum": {
    "name": "建连失败数-客户端RST",
    "unit": "NUMBER",
    "kpi": "failClientRstNum"
  },
  "failServerTimeoutNum": {
    "name": "建连失败数-服务器超时",
    "unit": "NUMBER",
    "kpi": "failServerTimeoutNum"
  },
  "failClientTimeoutNum": {
    "name": "建连失败数-客户端超时",
    "unit": "NUMBER",
    "kpi": "failClientTimeoutNum"
  },
  "lastSynIpId": {
    "name": "SYN IP.id",
    "unit": "NUMBER",
    "kpi": "lastSynIpId"
  },
  "lastSynSeqNum": {
    "name": "SYN TCP.seq",
    "unit": "NUMBER",
    "kpi": "lastSynSeqNum"
  },
  "successfulTcpConnNum": {
    "name": "建连成功数",
    "unit": "NUMBER",
    "kpi": "successfulTcpConnNum"
  },
  "totalSegLostPercent": {
    "name": "丢包率",
    "unit": "PERCENT",
    "kpi": "totalSegLostPercent"
  },
  "serverRespNum": {
    "name": "响应数",
    "unit": "NUMBER",
    "kpi": "serverRespNum"
  },
  "successfulTrans": {
    "name": "TCP交易数",
    "unit": "NUMBER",
    "kpi": "successfulTrans"
  },
  "connTime": { "name": "网络延迟", "unit": "US", "kpi": "connTime" },
  "clientConnTime": {
    "name": "客户端延迟",
    "unit": "US",
    "kpi": "clientConnTime"
  },
  "serverConnTime": {
    "name": "服务器延迟",
    "unit": "US",
    "kpi": "serverConnTime"
  },
  "ackDelayTimeAvg": {
    "name": "ACK 延时",
    "unit": "US",
    "kpi": "ackDelayTimeAvg"
  },
  "clientAckDelayTimeAvg": {
    "name": "客户端ACK延时",
    "unit": "US",
    "kpi": "clientAckDelayTimeAvg"
  },
  "serverAckDelayTimeAvg": {
    "name": "服务器ACK延时",
    "unit": "US",
    "kpi": "serverAckDelayTimeAvg"
  },
  "clientRespTimeAvg": {
    "name": "客户端响应时间",
    "unit": "US",
    "kpi": "clientRespTimeAvg"
  },
  "avgTransRespTime": {
    "name": "服务器响应时间",
    "unit": "US",
    "kpi": "avgTransRespTime"
  },
  "transRespTime": {
    "name": "总响应时间",
    "unit": "US",
    "kpi": "transRespTime"
  },
  "peakTransRespTime": {
    "name": "峰值响应时间",
    "unit": "US",
    "kpi": "peakTransRespTime"
  },
  "firstTransRespTime": {
    "name": "首次响应时间",
    "unit": "US",
    "kpi": "firstTransRespTime"
  },
  "clientTransferTime": {
    "name": "客户端请求平均传输时间",
    "unit": "US",
    "kpi": "clientTransferTime"
  },
  "serverTransferTime": {
    "name": "服务器响应平均传输时间",
    "unit": "US",
    "kpi": "serverTransferTime"
  },
  "timeDuration": { "name": "持续时间", "unit": "US", "kpi": "timeDuration" },
  "clientLocation": {
    "name": "源位置",
    "unit": "STRING",
    "kpi": "clientLocation"
  },
  "serverLocation": {
    "name": "目的位置",
    "unit": "STRING",
    "kpi": "serverLocation"
  },
  "clientIsp": { "name": "源ISP", "unit": "STRING", "kpi": "clientIsp" },
  "serverIsp": { "name": "目的ISP", "unit": "STRING", "kpi": "serverIsp" },
  "clientMac": { "name": "源MAC", "unit": "STRING", "kpi": "clientMac" },
  "serverMac": { "name": "目的MAC", "unit": "STRING", "kpi": "serverMac" },
  "clientMacVendor": {
    "name": "源MAC厂商",
    "unit": "STRING",
    "kpi": "clientMacVendor"
  },
  "serverMacVendor": {
    "name": "目的MAC厂商",
    "unit": "STRING",
    "kpi": "serverMacVendor"
  },
  "egressSrcIp": {
    "name": "Underlay上行源IP",
    "unit": "STRING",
    "kpi": "egressSrcIp"
  },
  "egressSrcPort": {
    "name": "Underlay上行源端口",
    "unit": "STRING",
    "kpi": "egressSrcPort"
  },
  "egressDstIp": {
    "name": "Underlay上行目的IP",
    "unit": "STRING",
    "kpi": "egressDstIp"
  },
  "egressDstPort": {
    "name": "Underlay上行目的端口",
    "unit": "STRING",
    "kpi": "egressDstPort"
  },
  "ingressSrcIp": {
    "name": "Underlay下行源IP",
    "unit": "STRING",
    "kpi": "ingressSrcIp"
  },
  "ingressSrcPort": {
    "name": "Underlay下行源端口",
    "unit": "STRING",
    "kpi": "ingressSrcPort"
  },
  "ingressDstIp": {
    "name": "Underlay下行目的IP",
    "unit": "STRING",
    "kpi": "ingressDstIp"
  },
  "ingressDstPort": {
    "name": "Underlay下行目的端口",
    "unit": "STRING",
    "kpi": "ingressDstPort"
  },
  "dpiCategory": {
    "name": "App协议类型",
    "unit": "STRING",
    "kpi": "dpiCategory"
  },
  "dpiProtocol": {
    "name": "App协议名",
    "unit": "STRING",
    "kpi": "dpiProtocol"
  },
  "clientSegLostPercent": {
    "name": "下行丢包率",
    "unit": "PERCENT",
    "kpi": "clientSegLostPercent"
  },
  "serverSegLostPercent": {
    "name": "上行丢包率",
    "unit": "PERCENT",
    "kpi": "serverSegLostPercent"
  },
  "outOfOrderNum": {
    "name": "乱序包数",
    "unit": "NUMBER",
    "kpi": "outOfOrderNum"
  },
  "outOfOrderPercent": {
    "name": "乱序率",
    "unit": "PERCENT",
    "kpi": "outOfOrderPercent"
  },
  "pingDropNum": {
    "name": "ICMP丢包数",
    "unit": "NUMBER",
    "kpi": "pingDropNum"
  },
  "avgPingRespTime": {
    "name": "ICMP平均响应时间",
    "unit": "US",
    "kpi": "avgPingRespTime"
  },
  "peakPingRespTime": {
    "name": "ICMP峰值响应时间",
    "unit": "US",
    "kpi": "peakPingRespTime"
  },
  "valleyPingRespTime": {
    "name": "ICMP谷值响应时间",
    "unit": "US",
    "kpi": "valleyPingRespTime"
  },
  "pingDropPercent": {
    "name": "ICMP丢包率",
    "unit": "PERCENT",
    "kpi": "pingDropPercent"
  },
  "clientFirstTTL": {
    "name": "客户端操作系统",
    "unit": "NUMBER",
    "kpi": "clientFirstTTL"
  },
  "serverFirstTTL": {
    "name": "服务器操作系统",
    "unit": "NUMBER",
    "kpi": "serverFirstTTL"
  }
}
